pytoma/cli.py
pytoma/collect.py
pytoma/config.py
pytoma/core.py
pytoma/edits.py
pytoma/ir.py
pytoma/log.py
pytoma/markers.py
pytoma/policies.py
pytoma/pre_resolution.py
pytoma/prompts.py
pytoma/render.py
pytoma/scan.py
pytoma/utils.py
pytoma/configs/skeleton.yaml
pytoma/engines/markdown_engine.py
pytoma/engines/markdown_naive.py
pytoma/engines/python_engine.py
pytoma/engines/toml_engine.py
pytoma/engines/xml_engine.py
pytoma-0.1.0a6.dist-info/METADATA
pytoma-0.1.0a6.dist-info/WHEEL
pytoma-0.1.0a6.dist-info/entry_points.txt
pytoma-0.1.0a6.dist-info/licenses/LICENSE
pytoma-0.1.0a6.dist-info/RECORD
