Metadata-Version: 2.4
Name: pytoma
Version: 0.1.0a6
Summary: Render a repo into one LLM-ready text file
Project-URL: Homepage, https://github.com/nathanap2/pytoma
Author-email: Nathan Palluau <nathan.palluau@gmail.com>
License: Copyright 2025 Nathan Palluau
License-File: LICENSE
Keywords: LLM,code-slicing,developer-tools,prompting,repo-pack
Classifier: Development Status :: 3 - Alpha
Classifier: Intended Audience :: Developers
Classifier: License :: OSI Approved :: MIT License
Classifier: Operating System :: OS Independent
Classifier: Programming Language :: Python :: 3
Classifier: Programming Language :: Python :: 3 :: Only
Classifier: Programming Language :: Python :: 3.9
Classifier: Programming Language :: Python :: 3.10
Classifier: Programming Language :: Python :: 3.11
Classifier: Programming Language :: Python :: 3.12
Classifier: Topic :: Software Development :: Build Tools
Requires-Python: >=3.9
Requires-Dist: libcst>=1.4
Requires-Dist: pyyaml>=6.0
